bojan/__init__.py
bojan/src/__init__.py
bojan/src/bojan.py
bojan-0.0.20.dist-info/LICENSE.txt
bojan-0.0.20.dist-info/METADATA
bojan-0.0.20.dist-info/WHEEL
bojan-0.0.20.dist-info/top_level.txt
bojan-0.0.20.dist-info/RECORD
