Metadata-Version: 2.1
Name: bojan
Version: 0.0.20
Summary: A simple logging library
Home-page: https://github.com/daniilgrydin/bojan.git
Author: Daniil Grydin
Author-email: 
License: MIT
Classifier: Programming Language :: Python :: 3
Classifier: License :: OSI Approved :: MIT License
Classifier: Operating System :: OS Independent
Requires-Python: >=3.6
License-File: LICENSE.txt
Provides-Extra: dev
Requires-Dist: pytest>=7.0; extra == "dev"
Requires-Dist: twine>=4.0.2; extra == "dev"
